{
  "label": "pilot_01",
  "created_at": "2026-05-19T11:42:56.633444+00:00",
  "conditions": [
    "HP_OFF"
  ],
  "n_runs": 1,
  "base_seed": 999,
  "n_workers": 1,
  "n_gens": 3,
  "runs": [
    {
      "condition": "HP_OFF",
      "seed": 999,
      "status": "complete",
      "output_dir": "/home/max/IdeaProjects/Sussex Uni/Year 4/Adaptive Systems/SussexMCOMP_AdaptiveSystems_Assignment2/experiments/pilot_01/hp_off_s999",
      "completed_at": "2026-05-19T11:44:05.641680+00:00",
      "final_best_fitness": 0.4877172715348538
    }
  ],
  "completed_at": "2026-05-19T11:44:05.641918+00:00"
}